rsyncfilter/__init__.py
rsyncfilter/src.py
rsyncfilter-2024.6.4.dist-info/METADATA
rsyncfilter-2024.6.4.dist-info/WHEEL
rsyncfilter-2024.6.4.dist-info/licenses/LICENSE
rsyncfilter-2024.6.4.dist-info/RECORD
