Metadata-Version: 2.4
Name: rsyncfilter
Version: 2024.6.4
Summary: A Python module for parsing .rsync-filter files
Project-URL: Repository, https://github.com/presto8/python-rsync-filter
Author-email: Preston Hunt <me@prestonhunt.com>
Maintainer-email: Preston Hunt <me@prestonhunt.com>
License-File: LICENSE
Classifier: Development Status :: 4 - Beta
Classifier: Intended Audience :: Developers
Classifier: License :: OSI Approved :: GNU General Public License v3 or later (GPLv3+)
Classifier: Programming Language :: Python :: 3.9
Requires-Python: >=3.9
